INEGIpy/__init__.py
INEGIpy/_denue.py
INEGIpy/_indicadores.py
INEGIpy/_marco_geoestadistico.py
INEGIpy/_ruteo.py
INEGIpy-1.2.1.dist-info/LICENSE
INEGIpy-1.2.1.dist-info/METADATA
INEGIpy-1.2.1.dist-info/WHEEL
INEGIpy-1.2.1.dist-info/top_level.txt
INEGIpy-1.2.1.dist-info/RECORD
