Metadata-Version: 2.1
Name: INEGIpy
Version: 1.2.1
Summary: Librería en Python para facilitar el uso de las APIs del INEGI
Home-page: https://github.com/andreslomeliv/DatosMex/tree/master/INEGIpy
Author: Andres Lomelí Viramontes
Author-email: andres.lomeli.v@gmail.com
License: MIT
Requires-Python: >=3.6.0
License-File: LICENSE
Requires-Dist: requests
Requires-Dist: pandas
Requires-Dist: numpy
Requires-Dist: geopandas
Requires-Dist: shapely
